django_static_bootstrap/.DS_Store
django_static_bootstrap/__init__.py
django_static_bootstrap/admin.py
django_static_bootstrap/apps.py
django_static_bootstrap/models.py
django_static_bootstrap/tests.py
django_static_bootstrap/views.py
django_static_bootstrap/migrations/__init__.py
django_static_bootstrap/static/.DS_Store
django_static_bootstrap/static/bootstrap/.DS_Store
django_static_bootstrap/static/bootstrap/css/bootstrap-grid.css
django_static_bootstrap/static/bootstrap/css/bootstrap-grid.css.map
django_static_bootstrap/static/bootstrap/css/bootstrap-grid.min.css
django_static_bootstrap/static/bootstrap/css/bootstrap-grid.min.css.map
django_static_bootstrap/static/bootstrap/css/bootstrap-reboot.css
django_static_bootstrap/static/bootstrap/css/bootstrap-reboot.css.map
django_static_bootstrap/static/bootstrap/css/bootstrap-reboot.min.css
django_static_bootstrap/static/bootstrap/css/bootstrap-reboot.min.css.map
django_static_bootstrap/static/bootstrap/css/bootstrap.css
django_static_bootstrap/static/bootstrap/css/bootstrap.css.map
django_static_bootstrap/static/bootstrap/css/bootstrap.min.css
django_static_bootstrap/static/bootstrap/css/bootstrap.min.css.map
django_static_bootstrap/static/bootstrap/js/bootstrap.bundle.js
django_static_bootstrap/static/bootstrap/js/bootstrap.bundle.js.map
django_static_bootstrap/static/bootstrap/js/bootstrap.bundle.min.js
django_static_bootstrap/static/bootstrap/js/bootstrap.bundle.min.js.map
django_static_bootstrap/static/bootstrap/js/bootstrap.js
django_static_bootstrap/static/bootstrap/js/bootstrap.js.map
django_static_bootstrap/static/bootstrap/js/bootstrap.min.js
django_static_bootstrap/static/bootstrap/js/bootstrap.min.js.map
django_static_bootstrap-4.6.2.2.dist-info/licenses/LICENSE
django_static_bootstrap-4.6.2.2.dist-info/METADATA
django_static_bootstrap-4.6.2.2.dist-info/WHEEL
django_static_bootstrap-4.6.2.2.dist-info/top_level.txt
django_static_bootstrap-4.6.2.2.dist-info/RECORD
